hivae/VAE_functions.py
hivae/__init__.py
hivae/graph_new.py
hivae/hivae.py
hivae/loglik_models_missing_normalize.py
hivae/model_HIVAE_factorized.py
hivae/model_HIVAE_inputDropout.py
hivae/parser_arguments.py
hivae/read_functions.py
hivae/utils.py
hivae-0.19.dist-info/LICENSE
hivae-0.19.dist-info/METADATA
hivae-0.19.dist-info/WHEEL
hivae-0.19.dist-info/top_level.txt
hivae-0.19.dist-info/RECORD
