Metadata-Version: 2.1
Name: hivae
Version: 0.19
Summary: HIVAE (Handling incomplete heterogeneous data using VAEs. - by Nazabal, et al., DOI: 10.1016/j.patcog.2020.107501, 2020) - Extenstion of implementations as easy to use Python library
Home-page: https://github.com/gkoutos-group/hivae/
Author: Andreas Karwath
Author-email: a.karwath@bham.ac.uk
License: MIT
Platform: UNKNOWN
Requires-Dist: tensorflow (<2,>=1.13.0)
Requires-Dist: pandas
Requires-Dist: sklearn
